<?xml version="1.0"?>
<!DOCTYPE informalfigure PUBLIC "-//OASIS//DTD DocBook XML V4.1.2//EN" "http://www.oasis-open.org/docbook/xml/4.1.2/docbookx.dtd">
<informalfigure><mediaobject><imageobject><imagedata fileref="watarun.eps" srccredit="Norman Walsh, 1998"/></imageobject><textobject><phrase>Wat Arun</phrase></textobject><caption><para>Wat Arun, Temple of the Dawn, on the Chao Phraya River
in Bangkok,
Thailand. In April, 1998, Wat Arun was in the midst of renovation.</para></caption></mediaobject></informalfigure>
